__init__.py
colab_grading_client.py
colab_grading_client-0.1.3.dist-info/licenses/LICENSE
colab_grading_client-0.1.3.dist-info/METADATA
colab_grading_client-0.1.3.dist-info/WHEEL
colab_grading_client-0.1.3.dist-info/top_level.txt
colab_grading_client-0.1.3.dist-info/RECORD
